packet_maze/__init__.py
packet_maze/packet_maze.c
packet_maze/packet_maze.py
packet_maze-0.1.1.dist-info/LICENSE
packet_maze-0.1.1.dist-info/METADATA
packet_maze-0.1.1.dist-info/WHEEL
packet_maze-0.1.1.dist-info/entry_points.txt
packet_maze-0.1.1.dist-info/top_level.txt
packet_maze-0.1.1.dist-info/zip-safe
packet_maze-0.1.1.dist-info/RECORD
