Metadata-Version: 2.1
Name: packet-maze
Version: 0.1.1
Summary: An interactive training tool for budding network programming enthousiast's!
Home-page: https://github.com/ArchiMoebius/packet-maze
Download-URL: https://github.com/ArchiMoebius/packet-maze
Author: Archi Moebius
Author-email: ArchiMoebius@dojobebo.com
Maintainer: Archi Moebius
Maintainer-email: ArchiMoebius@dojobebo.com
License: GPL-3 LGPL-3
Project-URL: Docs, https://github.com/ArchiMoebius/packet-maze/README.md
Project-URL: Bugs, https://github.com/ArchiMoebius/packet-maze/issues
Project-URL: C.I., https://github.com/ArchiMoebius/packet-maze/
Keywords: python3
Platform: Linux
Classifier: Development Status :: 1 - Planning
Classifier: Environment :: Console
Classifier: Environment :: Other Environment
Classifier: Intended Audience :: Developers
Classifier: Intended Audience :: Other Audience
Classifier: Natural Language :: English
Classifier: License :: OSI Approved :: GNU General Public License (GPL)
Classifier: License :: OSI Approved :: GNU Library or Lesser General Public License (LGPL)
Classifier: License :: OSI Approved :: GNU Lesser General Public License v3 or later (LGPLv3+)
Classifier: License :: OSI Approved :: GNU General Public License v3 or later (GPLv3+)
Classifier: Operating System :: POSIX :: Linux
Classifier: Programming Language :: Python
Classifier: Programming Language :: Python :: 3
Classifier: Programming Language :: Python :: 3 :: Only
Classifier: Programming Language :: Python :: 3.8
Classifier: Topic :: Software Development
Provides: packet_maze
Requires-Python: >=3.8
License-File: LICENSE
Requires-Dist: pip
Requires-Dist: scapy (>=2.4.5)
Requires-Dist: rich (>=12.5.1)
